sorcha/__init__.py
sorcha/_version.py
sorcha/sorcha.py
sorcha/activity/__init__.py
sorcha/activity/activity_registration.py
sorcha/activity/base_activity.py
sorcha/activity/identity_activity.py
sorcha/data/demo/baseline_v2.0_1yr.db
sorcha/data/demo/sorcha_config_demo.ini
sorcha/data/demo/sspp_testset_colours.txt
sorcha/data/demo/sspp_testset_orbits.des
sorcha/data/survey_setups/README.md
sorcha/data/survey_setups/Rubin_circular_approximation.ini
sorcha/data/survey_setups/Rubin_full_footprint.ini
sorcha/data/survey_setups/Rubin_known_object_prediction.ini
sorcha/ephemeris/__init__.py
sorcha/ephemeris/orbit_conversion_utilities.py
sorcha/ephemeris/pixel_dict.py
sorcha/ephemeris/simulation_constants.py
sorcha/ephemeris/simulation_data_files.py
sorcha/ephemeris/simulation_driver.py
sorcha/ephemeris/simulation_geometry.py
sorcha/ephemeris/simulation_parsing.py
sorcha/ephemeris/simulation_setup.py
sorcha/lightcurves/__init__.py
sorcha/lightcurves/base_lightcurve.py
sorcha/lightcurves/identity_lightcurve.py
sorcha/lightcurves/lightcurve_registration.py
sorcha/modules/PPAddUncertainties.py
sorcha/modules/PPApplyColourOffsets.py
sorcha/modules/PPApplyFOVFilter.py
sorcha/modules/PPBrightLimit.py
sorcha/modules/PPCalculateApparentMagnitude.py
sorcha/modules/PPCalculateApparentMagnitudeInFilter.py
sorcha/modules/PPCalculateSimpleCometaryMagnitude.py
sorcha/modules/PPDetectionEfficiency.py
sorcha/modules/PPDetectionProbability.py
sorcha/modules/PPDropObservations.py
sorcha/modules/PPFadingFunctionFilter.py
sorcha/modules/PPFaintObjectCullingFilter.py
sorcha/modules/PPFootprintFilter.py
sorcha/modules/PPGetMainFilterAndColourOffsets.py
sorcha/modules/PPLinkingFilter.py
sorcha/modules/PPMagnitudeLimit.py
sorcha/modules/PPMatchPointingToObservations.py
sorcha/modules/PPMiniDifi.py
sorcha/modules/PPOutput.py
sorcha/modules/PPRandomizeMeasurements.py
sorcha/modules/PPReadPointingDatabase.py
sorcha/modules/PPSNRLimit.py
sorcha/modules/PPStats.py
sorcha/modules/PPTrailingLoss.py
sorcha-1.1.0.dist-info/licenses/LICENSE.txt
sorcha-1.1.0.dist-info/METADATA
sorcha-1.1.0.dist-info/WHEEL
sorcha-1.1.0.dist-info/entry_points.txt
sorcha-1.1.0.dist-info/top_level.txt
sorcha-1.1.0.dist-info/RECORD
