Metadata-Version: 2.4
Name: sorcha
Version: 1.1.0
Summary: The survey simulator post processing code for the LSST
Author-email: Meg Schwamb <m.schwamb@qub.ac.uk>
License: Copyright 2023,2024, 2025 Sorcha Development Team
Project-URL: Documentation, https://sorcha.readthedocs.io/en/latest/
Project-URL: Source, https://github.com/dirac-institute/sorcha
Classifier: Intended Audience :: Science/Research
Classifier: License :: OSI Approved :: GNU General Public License v3 (GPLv3)
Classifier: Operating System :: OS Independent
Classifier: Programming Language :: Python
Classifier: Programming Language :: Python :: 3
Classifier: Programming Language :: Python :: 3.9
Classifier: Programming Language :: Python :: 3.10
Classifier: Programming Language :: Python :: 3.11
Classifier: Topic :: Scientific/Engineering :: Astronomy
Classifier: Topic :: Scientific/Engineering :: Physics
Requires-Python: >=3.9
License-File: LICENSE.txt
Requires-Dist: numpy
Requires-Dist: pandas>=2.0
Requires-Dist: astropy
Requires-Dist: matplotlib
Requires-Dist: sbpy
Requires-Dist: tables
Requires-Dist: spiceypy
Requires-Dist: healpy
Requires-Dist: assist
Requires-Dist: rebound
Requires-Dist: pooch
Requires-Dist: tqdm
Requires-Dist: numba
Requires-Dist: importlib_resources
Requires-Dist: scipy
Provides-Extra: dev
Requires-Dist: pytest; extra == "dev"
Requires-Dist: pytest-cov; extra == "dev"
Requires-Dist: pre-commit; extra == "dev"
Requires-Dist: sphinx; extra == "dev"
Requires-Dist: sphinx-rtd-theme; extra == "dev"
Requires-Dist: sphinx-exec-directive; extra == "dev"
Requires-Dist: sphinx-autoapi; extra == "dev"
Requires-Dist: black; extra == "dev"
Requires-Dist: nbconvert; extra == "dev"
Requires-Dist: nbsphinx; extra == "dev"
Requires-Dist: ipython; extra == "dev"
Requires-Dist: ipykernel; extra == "dev"
Requires-Dist: matplotlib; extra == "dev"
Requires-Dist: sorcha-addons; extra == "dev"
Requires-Dist: seaborn; extra == "dev"
Requires-Dist: jupyter; extra == "dev"
Provides-Extra: test
Requires-Dist: pytest; extra == "test"
Requires-Dist: pytest-cov; extra == "test"
Requires-Dist: black; extra == "test"
Provides-Extra: docs
Requires-Dist: sphinx; extra == "docs"
Requires-Dist: sphinx-rtd-theme; extra == "docs"
Requires-Dist: sphinx-autoapi; extra == "docs"
Requires-Dist: sphinx-exec-directive; extra == "docs"
Requires-Dist: nbconvert; extra == "docs"
Requires-Dist: nbsphinx; extra == "docs"
Requires-Dist: ipython; extra == "docs"
Requires-Dist: ipykernel; extra == "docs"
Provides-Extra: benchmark
Requires-Dist: lf-metric-emitter; extra == "benchmark"
Requires-Dist: memory-profiler; extra == "benchmark"
Dynamic: license-file
